ghweekly/__init__.py
ghweekly/cli.py
ghweekly/main.py
ghweekly-0.1.5.dist-info/licenses/LICENSE
ghweekly-0.1.5.dist-info/METADATA
ghweekly-0.1.5.dist-info/WHEEL
ghweekly-0.1.5.dist-info/entry_points.txt
ghweekly-0.1.5.dist-info/top_level.txt
ghweekly-0.1.5.dist-info/RECORD
