Metadata-Version: 2.4
Name: ghweekly
Version: 0.1.5
Summary: Visualize weekly GitHub commit activity across repositories.
Home-page: https://github.com/bhimrazy/gh-weekly-commits
Author: Bhimraj Yadav
License-Expression: MIT
Project-URL: Homepage, https://github.com/bhimrazy/gh-weekly-commits
Project-URL: BugTracker, https://github.com/bhimrazy/gh-weekly-commits/issues
Project-URL: Documentation, https://github.com/bhimrazy/gh-weekly-commits#readme
Project-URL: Source, https://github.com/bhimrazy/gh-weekly-commits
Requires-Python: >=3.10
License-File: LICENSE
Requires-Dist: requests
Requires-Dist: pandas
Requires-Dist: matplotlib
Provides-Extra: dev
Requires-Dist: ruff; extra == "dev"
Requires-Dist: pytest; extra == "dev"
Requires-Dist: coverage; extra == "dev"
Requires-Dist: pytest-cov; extra == "dev"
Dynamic: home-page
Dynamic: license-file
